aipyapp/__init__.py
aipyapp/__main__.py
aipyapp/__version__.py
aipyapp/i18n.py
aipyapp/interface.py
aipyapp/plugin.py
aipyapp/runtime.py
aipyapp/aipy/__init__.py
aipyapp/aipy/agent_taskmgr.py
aipyapp/aipy/blocks.py
aipyapp/aipy/cache.py
aipyapp/aipy/config.py
aipyapp/aipy/context_manager.py
aipyapp/aipy/diagnose.py
aipyapp/aipy/event_recorder.py
aipyapp/aipy/event_serializer.py
aipyapp/aipy/functions.py
aipyapp/aipy/libmcp.py
aipyapp/aipy/llm.py
aipyapp/aipy/mcp_tool.py
aipyapp/aipy/multimodal.py
aipyapp/aipy/plugins.py
aipyapp/aipy/prompts.py
aipyapp/aipy/role.py
aipyapp/aipy/runtime.py
aipyapp/aipy/step_manager.py
aipyapp/aipy/task.py
aipyapp/aipy/task_state.py
aipyapp/aipy/taskmgr.py
aipyapp/aipy/trustoken.py
aipyapp/aipy/utils.py
aipyapp/aipy/wizard.py
aipyapp/cli/__init__.py
aipyapp/cli/cli_agent.py
aipyapp/cli/cli_ipython.py
aipyapp/cli/cli_python.py
aipyapp/cli/cli_task.py
aipyapp/cli/command/__init__.py
aipyapp/cli/command/base.py
aipyapp/cli/command/common.py
aipyapp/cli/command/keybindings.py
aipyapp/cli/command/manager.py
aipyapp/cli/command/builtin/__init__.py
aipyapp/cli/command/builtin/cmd_block.py
aipyapp/cli/command/builtin/cmd_context.py
aipyapp/cli/command/builtin/cmd_custom.py
aipyapp/cli/command/builtin/cmd_display.py
aipyapp/cli/command/builtin/cmd_help.py
aipyapp/cli/command/builtin/cmd_info.py
aipyapp/cli/command/builtin/cmd_llm.py
aipyapp/cli/command/builtin/cmd_mcp.py
aipyapp/cli/command/builtin/cmd_plugin.py
aipyapp/cli/command/builtin/cmd_role.py
aipyapp/cli/command/builtin/cmd_steps.py
aipyapp/cli/command/builtin/cmd_task.py
aipyapp/cli/command/builtin/utils.py
aipyapp/cli/command/completer/__init__.py
aipyapp/cli/command/completer/argparse_completer.py
aipyapp/cli/command/completer/base.py
aipyapp/cli/command/completer/specialized.py
aipyapp/cli/command/custom/__init__.py
aipyapp/cli/command/custom/manager.py
aipyapp/cli/command/custom/markdown.py
aipyapp/config/__init__.py
aipyapp/config/base.py
aipyapp/config/llm.py
aipyapp-0.3.0.dist-info/METADATA
aipyapp-0.3.0.dist-info/WHEEL
aipyapp-0.3.0.dist-info/entry_points.txt
aipyapp-0.3.0.dist-info/licenses/LICENSE
aipyapp-0.3.0.dist-info/RECORD
