Metadata-Version: 2.4
Name: aipyapp
Version: 0.3.0
Summary: AIPyApp: AI-Powered Python & Python-Powered AI
License-File: LICENSE
Requires-Python: >=3.10
Requires-Dist: anthropic>=0.49.0
Requires-Dist: beautifulsoup4>=4.13.3
Requires-Dist: charset-normalizer>=3.4.2
Requires-Dist: dynaconf>=3.2.10
Requires-Dist: fastapi>=0.116.1
Requires-Dist: jinja2>=3.1.6
Requires-Dist: loguru>=0.7.3
Requires-Dist: mcp[cli]>=1.10.0
Requires-Dist: openai>=1.68.2
Requires-Dist: openpyxl>=3.1.5
Requires-Dist: pandas>=2.2.3
Requires-Dist: prompt-toolkit>=3.0.51
Requires-Dist: psutil>=7.0.0
Requires-Dist: pygments>=2.19.2
Requires-Dist: pyyaml>=6.0.2
Requires-Dist: qrcode>=8.1
Requires-Dist: questionary>=2.1.0
Requires-Dist: requests>=2.32.3
Requires-Dist: rich>=13.9.4
Requires-Dist: seaborn>=0.13.2
Requires-Dist: term-image>=0.7.2
Requires-Dist: tomli-w>=1.2.0
Provides-Extra: dev
Requires-Dist: pytest-asyncio>=0.23.0; extra == 'dev'
Requires-Dist: pytest-cov>=5.0.0; extra == 'dev'
Requires-Dist: pytest-mock>=3.14.0; extra == 'dev'
Requires-Dist: pytest-timeout>=2.3.0; extra == 'dev'
Requires-Dist: pytest-xdist>=3.6.0; extra == 'dev'
Requires-Dist: pytest>=8.0.0; extra == 'dev'
Requires-Dist: ruff>=0.8.0; extra == 'dev'
Provides-Extra: test
Requires-Dist: pytest-asyncio>=0.23.0; extra == 'test'
Requires-Dist: pytest-cov>=5.0.0; extra == 'test'
Requires-Dist: pytest-mock>=3.14.0; extra == 'test'
Requires-Dist: pytest-timeout>=2.3.0; extra == 'test'
Requires-Dist: pytest-xdist>=3.6.0; extra == 'test'
Requires-Dist: pytest>=8.0.0; extra == 'test'
